GumbraiseInstagram
README.md
setup.py
GumbraiseInstagram/GumbraiseInstagram.py
GumbraiseInstagram/__init__.py
GumbraiseInstagram/exceptions.py
GumbraiseInstagram.egg-info/PKG-INFO
GumbraiseInstagram.egg-info/SOURCES.txt
GumbraiseInstagram.egg-info/dependency_links.txt
GumbraiseInstagram.egg-info/top_level.txt