Metadata-Version: 2.1
Name: GumbraiseInstagram
Version: 0.1
Summary: A personnal Python Instagram API
Home-page: https://github.com/Gumbraise/InstagramAPI_python
Author: Gumbraise
Author-email: contact@kellis.fr
License: UNKNOWN
Platform: UNKNOWN
Classifier: Programming Language :: Python :: 3
Classifier: License :: OSI Approved :: MIT License
Classifier: Operating System :: OS Independent
